README.md
setup.py
pyojm/__init__.py
pyojm/attributes.py
pyojm/models.py
pyojm.egg-info/PKG-INFO
pyojm.egg-info/SOURCES.txt
pyojm.egg-info/dependency_links.txt
pyojm.egg-info/requires.txt
pyojm.egg-info/top_level.txt
tests/__init__.py
tests/test_pyojm.py