Metadata-Version: 1.0
Name: pyojm
Version: 0.1.0
Summary: A Pythonic Interface to Json.
Home-page: https://github.com/lune_sta/json-model
Author: lune*
Author-email: lune@wuvu.net
License: MIT
Keywords: json wrapper model
Platform: UNKNOWN
